{
  "nodes": [
    { "id": "kason_blackwood", "name": "Kason Blackwood", "gender": "male", "world": "Oasis Springs", "playable": true },
    { "id": "erica_green", "name": "Erica Green", "gender": "female", "world": "Evergreen Harbour", "playable": true },
    { "id": "thalia_hare", "name": "Thalia Hare", "gender": "female", "world": "Oasis Springs", "playable": true },
    { "id": "inez_calder", "name": "Inez Calder", "gender": "female", "world": "Oasis Springs", "playable": true },
    { "id": "olivia_hastings", "name": "Olivia Hastings", "gender": "female", "world": "Oasis Springs", "playable": true },
    { "id": "johnny_zest", "name": "Johnny Zest", "gender": "male", "world": "Oasis Springs", "playable": true },
    { "id": "isolde_kovac", "name": "Isolde Kovac", "gender": "female", "world": "Oasis Springs", "playable": true },
    { "id": "natasha_kovac", "name": "Natasha Kovac", "gender": "female", "world": "Oasis Springs", "playable": true },
    { "id": "yuri_kovac", "name": "Yuri Kovac", "gender": "male", "world": "Oasis Springs", "playable": true },
    { "id": "rinka_handa", "name": "Rinka Handa", "gender": "female", "world": "Mt Komorebi", "playable": true },
    { "id": "vladislaus_straud", "name": "Vladislaus Straud", "gender": "male", "world": "Forgotten Hollow", "playable": false },
    { "id": "david_jacobs", "name": "David Jacobs", "gender": "male", "world": "Willow Creek", "playable": true },
    { "id": "elaine_jacobs", "name": "Elaine Jacobs", "gender": "female", "world": "Willow Creek", "playable": true },
    { "id": "nate_jacobs", "name": "Nate Jacobs", "gender": "male", "world": "Willow Creek", "playable": true },
    { "id": "jason_jacobs", "name": "Jason Jacobs", "gender": "male", "world": "Willow Creek", "playable": true },
    { "id": "johannah_ridley", "name": "Johannah Ridley", "gender": "female", "world": "Willow Creek", "playable": true },
    { "id": "jodie_ridley", "name": "Jodie Ridley", "gender": "female", "world": "Willow Creek", "playable": true },
    { "id": "jade_ridley", "name": "Jade Ridley", "gender": "female", "world": "Willow Creek", "playable": true },
    { "id": "jonathan_ridley", "name": "Jonathan Ridley", "gender": "male", "world": "Willow Creek", "playable": true },
    { "id": "ethan_ridley", "name": "Ethan Ridley", "gender": "male", "world": "Willow Creek", "playable": true },
    { "id": "kamila_ridley", "name": "Kamila Ridley", "gender": "female", "world": "Willow Creek", "playable": true },
    { "id": "cedric_addams", "name": "Cedric Addams", "gender": "male", "world": "Willow Creek", "playable": true },
    { "id": "morticia_addams", "name": "Morticia Addams", "gender": "female", "world": "Willow Creek", "playable": true },
    { "id": "wednesday_addams", "name": "Wednesday Addams", "gender": "female", "world": "Willow Creek", "playable": true },
    { "id": "nichole_yoh", "name": "Nichole Yoh", "gender": "female", "world": "Del Sol Valley", "playable": true },
    { "id": "taehun_yoh", "name": "Taehun Yoh", "gender": "male", "world": "Del Sol Valley", "playable": true },
    { "id": "alfred_kvasnicka", "name": "Alfred Kvasnicka", "gender": "male", "world": "Del Sol Valley", "playable": true },
    { "id": "victoria_macallister", "name": "Victoria MacAllister", "gender": "female", "world": "Del Sol Valley", "playable": true },
    { "id": "nadia_macallister", "name": "Nadia MacAllister", "gender": "female", "world": "Del Sol Valley", "playable": true },
    { "id": "genos_carvelli", "name": "Genos Carvelli", "gender": "male", "world": "Del Sol Valley", "playable": true },
    { "id": "annabelle_usher", "name": "Annabelle Usher", "gender": "female", "world": "Del Sol Valley", "playable": false },
    { "id": "roderick_usher", "name": "Roderick Usher", "gender": "male", "world": "Del Sol Valley", "playable": true },
    { "id": "frederick_usher", "name": "Frederick Usher", "gender": "male", "world": "Del Sol Valley", "playable": true },
    { "id": "morella_usher", "name": "Morella Usher", "gender": "female", "world": "Del Sol Valley", "playable": true },
    { "id": "sabrina_faircroft", "name": "Sabrina Faircroft", "gender": "female", "world": "Henford-on-Bagley", "playable": true },
    { "id": "dorian_faircroft", "name": "Dorian Faircroft", "gender": "male", "world": "Henford-on-Bagley", "playable": true },
    { "id": "winona_faircroft", "name": "Winona Faircroft", "gender": "female", "world": "Henford-on-Bagley", "playable": true },
    { "id": "chayton_faircroft", "name": "Chayton Faircroft", "gender": "male", "world": "Henford-on-Bagley", "playable": true },
    { "id": "bartholomew_faircroft", "name": "Bartholomew Faircroft", "gender": "male", "world": "Henford-on-Bagley", "playable": true },
    { "id": "shalini_mehra", "name": "Shalini Mehra", "gender": "female", "world": "Del Sol Valley", "playable": true },
    { "id": "alessia_moretti", "name": "Alessia Moretti", "gender": "female", "world": "Del Sol Valley", "playable": true },
    { "id": "darius_rollins", "name": "Darius Rollins", "gender": "male", "world": "Oasis Springs", "playable": true },
    { "id": "shayla_rollins", "name": "Shayla Rollins", "gender": "female", "world": "Oasis Springs", "playable": true },
    { "id": "javante_rollins", "name": "Javante Rollins", "gender": "male", "world": "Oasis Springs", "playable": true },
    { "id": "latoya_freeman", "name": "Latoya Freeman", "gender": "female", "world": "Oasis Springs", "playable": true },
    { "id": "elias_freeman", "name": "Elias Freeman", "gender": "male", "world": "Oasis Springs", "playable": true },
    { "id": "deshawn_freeman", "name": "Deshawn Freeman", "gender": "male", "world": "Oasis Springs", "playable": true },
    { "id": "magdalena_alvarez", "name": "Magdalena Alvarez", "gender": "female", "world": "Copperdale", "playable": true },
    { "id": "cassie_schulz", "name": "Cassie Schulz", "gender": "female", "world": "Copperdale", "playable": true },
    { "id": "sloane_hayes", "name": "Sloane Hayes", "gender": "female", "world": "Willow Creek", "playable": true },
    { "id": "jorien_rembrandt", "name": "Jorien Rembrandt", "gender": "other", "world": "Willow Creek", "playable": true },
    { "id": "regina_king", "name": "Regina King", "gender": "female", "world": "Copperdale", "playable": true },
    { "id": "ink_reynolds", "name": "Ink Reynolds", "gender": "other", "world": "Prison", "playable": true },
    { "id": "dakota_grayhawk", "name": "Dakota Grayhawk", "gender": "male", "world": "Henford-on-Bagley", "playable": true },
    { "id": "parivita_bhatnagar", "name": "Parivita Bhatnagar", "gender": "female", "world": "Brindleton Bay", "playable": true },
    { "id": "oliana_moanikea", "name": "Oliana Moanikea", "gender": "female", "world": "Sulani", "playable": true },
    { "id": "malia_nohau", "name": "Malia Nohau", "gender": "female", "world": "Sulani", "playable": true },
    { "id": "hinaopele_anuhewa", "name": "Hinaopele Anuhewa", "gender": "female", "world": "Sulani", "playable": true },
    { "id": "nancy_landgraab", "name": "Nancy Landgraab", "gender": "female", "world": "Willow Creek", "playable": false },
    { "id": "barbie_roberts", "name": "Barbie Roberts", "gender": "female", "world": "Del Sol Valley", "playable": false },
    { "id": "dr_tesla_darwin", "name": "Dr. Tesla Darwin", "gender": "male", "world": "Strangerville", "playable": true },
    { "id": "varek_sanguine", "name": "Varek Sanguine", "gender": "male", "world": "Forgotten Hollow", "playable": true },
    { "id": "bellatrix_mireshade", "name": "Bellatrix Mireshade", "gender": "female", "world": "Forgotten Hollow", "playable": true },
    { "id": "toya_mochizuki", "name": "Toya Mochizuki", "gender": "male", "world": "Magic Realm", "playable": true },
    { "id": "ophelia_frump", "name": "Ophelia Frump", "gender": "female", "world": "Willow Creek", "playable": true },
    { "id": "brielle_delacroix", "name": "Brielle Delacroix", "gender": "female", "world": "Willow Creek", "playable": true }
  ],
  "links": [
    { "source": "kason_blackwood", "target": "erica_green", "type": "employer", "label": "Employer" },
    { "source": "kason_blackwood", "target": "thalia_hare", "type": "employer", "label": "Employer" },
    { "source": "kason_blackwood", "target": "inez_calder", "type": "employer", "label": "Employer" },
    { "source": "kason_blackwood", "target": "olivia_hastings", "type": "close", "label": "Close" },
    { "source": "kason_blackwood", "target": "johnny_zest", "type": "acquaintance", "label": "Acquaintance" },
    { "source": "kason_blackwood", "target": "vladislaus_straud", "type": "acquaintance", "label": "Acquaintance" },
    { "source": "kason_blackwood", "target": "rinka_handa", "type": "acquaintance", "label": "Acquaintance" },
    { "source": "erica_green", "target": "thalia_hare", "type": "friends", "label": "Friends" },
    { "source": "erica_green", "target": "inez_calder", "type": "friends", "label": "Friends" },
    { "source": "erica_green", "target": "olivia_hastings", "type": "friends", "label": "Friends" },
    { "source": "thalia_hare", "target": "inez_calder", "type": "friends", "label": "Friends" },
    { "source": "thalia_hare", "target": "olivia_hastings", "type": "friends", "label": "Friends" },
    { "source": "inez_calder", "target": "olivia_hastings", "type": "friends", "label": "Friends" },
    { "source": "johnny_zest", "target": "isolde_kovac", "type": "situationship", "label": "Situationship" },
    { "source": "johnny_zest", "target": "latoya_freeman", "type": "situationship", "label": "Situationship" },
    { "source": "johnny_zest", "target": "elias_freeman", "type": "gang", "label": "Gang" },
    { "source": "johnny_zest", "target": "deshawn_freeman", "type": "gang", "label": "Gang" },
    { "source": "johnny_zest", "target": "latoya_freeman", "type": "gang", "label": "Gang" },
    { "source": "isolde_kovac", "target": "natasha_kovac", "type": "siblings", "label": "Siblings" },
    { "source": "isolde_kovac", "target": "yuri_kovac", "type": "siblings", "label": "Siblings" },
    { "source": "natasha_kovac", "target": "yuri_kovac", "type": "siblings", "label": "Siblings" },
    { "source": "natasha_kovac", "target": "kason_blackwood", "type": "negative", "label": "Dislikes" },
    { "source": "isolde_kovac", "target": "ink_reynolds", "type": "friends", "label": "Friends" },
    { "source": "david_jacobs", "target": "elaine_jacobs", "type": "married", "label": "Married" },
    { "source": "david_jacobs", "target": "nate_jacobs", "type": "parent", "label": "Parent" },
    { "source": "david_jacobs", "target": "jason_jacobs", "type": "parent", "label": "Parent" },
    { "source": "nate_jacobs", "target": "magdalena_alvarez", "type": "dating", "label": "Dating" },
    { "source": "nate_jacobs", "target": "cassie_schulz", "type": "affair", "label": "Affair" },
    { "source": "cassie_schulz", "target": "magdalena_alvarez", "type": "best_friend", "label": "Best Friends" },
    { "source": "johannah_ridley", "target": "cedric_addams", "type": "dating", "label": "Dating" },
    { "source": "jade_ridley", "target": "sloane_hayes", "type": "in_love", "label": "In Love" },
    { "source": "jade_ridley", "target": "jorien_rembrandt", "type": "friends", "label": "Friends" },
    { "source": "jorien_rembrandt", "target": "sloane_hayes", "type": "friends", "label": "Friends" },
    { "source": "jorien_rembrandt", "target": "jade_ridley", "type": "in_love", "label": "In Love (secret)" },
    { "source": "jade_ridley", "target": "ink_reynolds", "type": "friends", "label": "Friends (secret)" },
    { "source": "jade_ridley", "target": "dakota_grayhawk", "type": "friends", "label": "Friends" },
    { "source": "jade_ridley", "target": "javante_rollins", "type": "friends", "label": "Friends" },
    { "source": "jodie_ridley", "target": "taehun_yoh", "type": "dating", "label": "Semi-Dating" },
    { "source": "jodie_ridley", "target": "regina_king", "type": "frenemy", "label": "Frenemy" },
    { "source": "taehun_yoh", "target": "regina_king", "type": "dating", "label": "On-Off" },
    { "source": "ethan_ridley", "target": "victoria_macallister", "type": "affair", "label": "Affair" },
    { "source": "nichole_yoh", "target": "taehun_yoh", "type": "parent", "label": "Parent" },
    { "source": "nichole_yoh", "target": "alfred_kvasnicka", "type": "best_friend", "label": "Best Friends" },
    { "source": "nichole_yoh", "target": "genos_carvelli", "type": "situationship", "label": "Situationship" },
    { "source": "nichole_yoh", "target": "shalini_mehra", "type": "friends", "label": "Friends" },
    { "source": "nadia_macallister", "target": "genos_carvelli", "type": "crush", "label": "Crush (secret)" },
    { "source": "annabelle_usher", "target": "nancy_landgraab", "type": "illuminati", "label": "Illuminati" },
    { "source": "annabelle_usher", "target": "barbie_roberts", "type": "illuminati", "label": "Illuminati" },
    { "source": "annabelle_usher", "target": "roderick_usher", "type": "married", "label": "Married" },
    { "source": "varek_sanguine", "target": "bellatrix_mireshade", "type": "best_friend", "label": "Best Friends" },
    { "source": "varek_sanguine", "target": "bartholomew_faircroft", "type": "transactional", "label": "Transactional" },
    { "source": "vladislaus_straud", "target": "bellatrix_mireshade", "type": "close", "label": "Close" },
    { "source": "toya_mochizuki", "target": "ophelia_frump", "type": "crush", "label": "Crush" },
    { "source": "morticia_addams", "target": "ophelia_frump", "type": "siblings", "label": "Siblings" },
    { "source": "parivita_bhatnagar", "target": "ink_reynolds", "type": "friends", "label": "Friends" },
    { "source": "darius_rollins", "target": "shayla_rollins", "type": "married", "label": "Married" },
    { "source": "darius_rollins", "target": "javante_rollins", "type": "parent", "label": "Parent" },
    { "source": "shayla_rollins", "target": "latoya_freeman", "type": "siblings", "label": "Siblings" },
    { "source": "shayla_rollins", "target": "elias_freeman", "type": "siblings", "label": "Siblings" },
    { "source": "shayla_rollins", "target": "deshawn_freeman", "type": "siblings", "label": "Siblings" },
    { "source": "oliana_moanikea", "target": "malia_nohau", "type": "best_friend", "label": "Best Friends" },
    { "source": "shalini_mehra", "target": "alessia_moretti", "type": "roommates", "label": "Roommates" },
    { "source": "dr_tesla_darwin", "target": "kason_blackwood", "type": "acquaintance", "label": "Acquaintance" }
  ]
}
